claude_collector/__init__.py
claude_collector/cli.py
claude_collector-0.1.0.dist-info/METADATA
claude_collector-0.1.0.dist-info/WHEEL
claude_collector-0.1.0.dist-info/entry_points.txt
claude_collector-0.1.0.dist-info/licenses/LICENSE
claude_collector-0.1.0.dist-info/RECORD
