Metadata-Version: 2.4
Name: claude-collector
Version: 0.1.0
Summary: Extract and sanitize Claude Code conversation data for training datasets
Project-URL: Homepage, https://github.com/hanzoai/claude-collector
Project-URL: Repository, https://github.com/hanzoai/claude-collector
Author-email: Hanzo AI <hello@hanzo.ai>
License: MIT
License-File: LICENSE
Keywords: ai,claude,dataset,llm,training
Classifier: Development Status :: 4 - Beta
Classifier: Intended Audience :: Developers
Classifier: License :: OSI Approved :: MIT License
Classifier: Programming Language :: Python :: 3
Classifier: Programming Language :: Python :: 3.8
Classifier: Programming Language :: Python :: 3.9
Classifier: Programming Language :: Python :: 3.10
Classifier: Programming Language :: Python :: 3.11
Classifier: Programming Language :: Python :: 3.12
Requires-Python: >=3.8
Requires-Dist: click>=8.0.0
Requires-Dist: rich>=13.0.0
